DesignSpark/__init__.py
DesignSpark/Cloud/Metrics.py
DesignSpark/Cloud/__init__.py
DesignSpark/Cloud/prometheus_pb2.py
DesignSpark/Cloud/validator.py
DesignSpark.Cloud-22.11.0.dist-info/LICENSE
DesignSpark.Cloud-22.11.0.dist-info/METADATA
DesignSpark.Cloud-22.11.0.dist-info/WHEEL
DesignSpark.Cloud-22.11.0.dist-info/top_level.txt
DesignSpark.Cloud-22.11.0.dist-info/RECORD
