Metadata-Version: 2.1
Name: DesignSpark.Cloud
Version: 22.11.0
Summary: DesignSpark Cloud support library
Author-email: RS Components <maint@abopen.com>
License: MIT License
Project-URL: Homepage, https://github.com/DesignSparkRS/DesignSpark.Cloud
Keywords: designspark,cloud
Classifier: Development Status :: 3 - Alpha
Classifier: Intended Audience :: Developers
Classifier: License :: OSI Approved :: MIT License
Classifier: Operating System :: POSIX :: Linux
Classifier: Programming Language :: Python :: 3
Classifier: Programming Language :: Python :: 3.7
Classifier: Topic :: Education
Classifier: Topic :: System :: Hardware
Classifier: Topic :: Software Development :: Libraries
Requires-Python: >=3.7
License-File: LICENSE
Requires-Dist: requests
Requires-Dist: python-snappy
Requires-Dist: protobuf (<3.20.1)
Requires-Dist: prometheus-api-client
